{
  "name": "Filtration Unit",
  "description": "Breaks down the impurities within bauxite to form aluminum, creating fluid mud in the process. Can also reprocess the mud into ashstone and bismuth.",
  "hasItems": true,
  "hasLiquids": true,
  "hasPower": true,
  "itemCapacity": 20,
  "liquidCapacity": 30,
  "type": "multicraft.MultiCrafter",
  "craftEffect": "smeltsmoke",
  "category": "crafting",
  "menu": "transform",
  "size": 2,
  "requirements": [
    {"item": "bismuth", "amount": 65},
    {"item": "ashstone", "amount": 35}
    ],
    "recipes": [
    {
      "input": "dragenisis-mud/0.9",
      "output": {
        "items": [
          "dragenisis-bismuth/1",
          "dragenisis-ashstone/2"
        ],
      },
      "craftTime": 7.5
    },
    {
      "input":{
        "items":[
          "dragenisis-bauxite/2"
        ],
        "power": 0.95
      },
      "output": {
        "fluids": [
          "dragenisis-mud/0.85"
        ],
        "items":[
          "dragenisis-aluminum/3"
        ],
      },
      "craftTime": 7.5
    }
  ]
}
