{
  "name": "Filtration Unit",
  "description": "Breaks down the impurities within bauxite to form aluminum, creating fluid mud in the process. Can also reprocess the mud into ashstone and bismuth.",
  "hasItems": true,
  "hasLiquids": true,
  "hasPower": true,
  "itemCapacity": 20,
  "liquidCapacity": 200,
  "type": "multicraft.MultiCrafter",
  "craftEffect": "smeltsmoke",
  "category": "crafting",
  "menu": "Transform",
  "size": 2,
  "breakable": "true",
  "requirements": [
    {"bismuth/65", "ashstone/35"}
    ],
    "recipes": [
    {
      "input":{
        "item": "bauxite/2"
      },
      "output":{
        "item": "aluminum/2", "fluids": "mud/4.5"
      },
      "craftTime": 75
    },
    {
      "input":{
        "fluids":[
          "mud/9",
          "power": 3.25
        ]
      },
      "output": {
        "item": [
          "ashstone/2", 
          "bismuth/1"
        ]
      },
      "craftTime": 100
    }
  ]
}
